{
  "Name": "CoRR",
  "BIDSVersion": "1.8.0",
  "Authors": [
    "Anderson, JS",
    "Bellec, P",
    "Birn, R",
    "Blautzik, J",
    "Breitner, JCS",
    "Buckner, R",
    "Calhoun, V",
    "Castellanos, FX",
    "Chen, A",
    "Chen, B",
    "Chen, J",
    "Chen, X",
    "Colcombe, SJ",
    "Craddock, C",
    "Di Martino, A",
    "Fu, X",
    "Gong, Q",
    "He, Y",
    "Jiang, T",
    "Kelly, C",
    "Kelley, W",
    "LaConte, SM",
    "Lainhart, JE",
    "Lei, X",
    "Li, HJ",
    "Li, Kaiming",
    "Li, Kuncheng",
    "Liu, D",
    "Liu, J",
    "Liu, X",
    "Liu, Y",
    "Lu, J",
    "Lu, G",
    "Luna, B",
    "Luo, J",
    "Mao, Y",
    "Mayer, AR",
    "Margulies, D",
    "Meindl, T",
    "Meyerand, ME",
    "Milham, MP",
    "Nan, W",
    "Nielsen, JA",
    "Paulsen, D",
    "Prabhakaran, V",
    "Qiu, J",
    "Shao, C",
    "Tang, W",
    "Villringer, A",
    "Wang, H",
    "Wang, K",
    "Wei, D",
    "Wei, GX",
    "Weng, X",
    "Wu, X",
    "Xu, T",
    "Yang, Z",
    "Zang, YF",
    "Zhang, Q",
    "Zhang, Z",
    "Zhao, K",
    "Zhen, Z",
    "Zhou, Y",
    "Zuo, XN"
  ],
  "ReferencesAndLinks": [
    "https://doi.org/10.1038/sdata.2014.49",
    "https://doi.org/10.1038/sdata.2014.54"
  ],
  "Acknowledgements":
    "https://fcon_1000.projects.nitrc.org/indi/CoRR/html/index.html"
}
